py_aws_code_artifact_tool/__init__.py
py_aws_code_artifact_tool/check_and_setup.py
py_aws_code_artifact_tool/cli.py
py_aws_code_artifact_tool/config.py
py_aws_code_artifact_tool/environment_vars.py
py_aws_code_artifact_tool/main.py
py_aws_code_artifact_tool/pip_code_artifact_setup.py
py_aws_code_artifact_tool/version.py
py_aws_code_artifact_tool-0.1.1.dist-info/METADATA
py_aws_code_artifact_tool-0.1.1.dist-info/WHEEL
py_aws_code_artifact_tool-0.1.1.dist-info/entry_points.txt
py_aws_code_artifact_tool-0.1.1.dist-info/licenses/LICENSE
py_aws_code_artifact_tool-0.1.1.dist-info/RECORD
