Metadata-Version: 2.4
Name: py_aws_code_artifact_tool
Version: 0.1.1
Summary: CLI tool for building and deploying Python projects to AWS CodeArtifact
Author-email: Eric Wilson <eric.wilson@geekcafe.com>
License-File: LICENSE
Requires-Python: >=3.8
Requires-Dist: build
Requires-Dist: toml
Requires-Dist: twine
